rke_score/__init__.py
rke_score/rke.py
rke_score-0.0.7.dist-info/LICENSE
rke_score-0.0.7.dist-info/METADATA
rke_score-0.0.7.dist-info/WHEEL
rke_score-0.0.7.dist-info/top_level.txt
rke_score-0.0.7.dist-info/RECORD
