Metadata-Version: 2.1
Name: rke-score
Version: 0.0.7
Summary: Compute Renyi Kernel Entropy scores (RKE-MC and RRKE) for two sets of vectors.
Home-page: https://github.com/mjalali/renyi-kernel-entropy-score
Author: 
License: MIT
Classifier: Programming Language :: Python :: 3.10
Classifier: License :: OSI Approved :: MIT License
Classifier: Operating System :: OS Independent
License-File: LICENSE
Requires-Dist: numpy
